MANIFEST.in
README.txt
setup.py
cmsplugin_blog/__init__.py
cmsplugin_blog/admin.py
cmsplugin_blog/cms_app.py
cmsplugin_blog/cms_plugins.py
cmsplugin_blog/feeds.py
cmsplugin_blog/middleware.py
cmsplugin_blog/models.py
cmsplugin_blog/simple_translate.py
cmsplugin_blog/sitemaps.py
cmsplugin_blog/urls.py
cmsplugin_blog/utils.py
cmsplugin_blog/views.py
cmsplugin_blog/widgets.py
cmsplugin_blog.egg-info/PKG-INFO
cmsplugin_blog.egg-info/SOURCES.txt
cmsplugin_blog.egg-info/dependency_links.txt
cmsplugin_blog.egg-info/not-zip-safe
cmsplugin_blog.egg-info/requires.txt
cmsplugin_blog.egg-info/top_level.txt
cmsplugin_blog/locale/de/LC_MESSAGES/django.mo
cmsplugin_blog/locale/de/LC_MESSAGES/django.po
cmsplugin_blog/locale/en/LC_MESSAGES/django.mo
cmsplugin_blog/locale/en/LC_MESSAGES/django.po
cmsplugin_blog/locale/nb/LC_MESSAGES/django.mo
cmsplugin_blog/locale/nb/LC_MESSAGES/django.po
cmsplugin_blog/locale/pl/LC_MESSAGES/django.mo
cmsplugin_blog/locale/pl/LC_MESSAGES/django.po
cmsplugin_blog/locale/ru/LC_MESSAGES/django.mo
cmsplugin_blog/locale/ru/LC_MESSAGES/django.po
cmsplugin_blog/migrations/0001_initial.py
cmsplugin_blog/migrations/0002_auto__add_field_entry_pub_date.py
cmsplugin_blog/migrations/0003_auto__add_field_entry_is_published.py
cmsplugin_blog/migrations/0004_auto__add_pygmentsplugin.py
cmsplugin_blog/migrations/0005_auto__add_latestentriesplugin.py
cmsplugin_blog/migrations/0006_auto__add_field_entry_tags.py
cmsplugin_blog/migrations/0007_auto__del_pygmentsplugin__chg_field_entry_tags.py
cmsplugin_blog/migrations/0008_removed_placeholder.py
cmsplugin_blog/migrations/0009_added_manytomany_to_placeholder.py
cmsplugin_blog/migrations/0010_auto__add_unique_entrytitle_slug.py
cmsplugin_blog/migrations/0011_auto__add_field_entrytitle_author.py
cmsplugin_blog/migrations/0012_auto__chg_field_entrytitle_language.py
cmsplugin_blog/migrations/0013_auto__chg_field_entrytitle_slug.py
cmsplugin_blog/migrations/0014_auto__del_unique_entrytitle_slug__add_unique_entrytitle_slug_language.py
cmsplugin_blog/migrations/0015_auto__add_field_latestentriesplug.py
cmsplugin_blog/migrations/__init__.py
cmsplugin_blog/static/cmsplugin_blog/change_form.js
cmsplugin_blog/static/cmsplugin_blog/cmsplugin_blog.css
