Metadata-Version: 1.0
Name: cmsplugin-blog
Version: 1.1.2
Summary: This is a blog app/plugin for django-cms 2.2
Home-page: http://github.com/fivethreeo/cmsplugin-blog/
Author: Oyvind Saltvik
Author-email: oyvind.saltvik@gmail.com
License: UNKNOWN
Platform: UNKNOWN
Classifier: Development Status :: 5 - Production/Stable
Classifier: Environment :: Web Environment
Classifier: Intended Audience :: Developers
Classifier: License :: OSI Approved :: BSD License
Classifier: Operating System :: OS Independent
Classifier: Programming Language :: Python
Classifier: Framework :: Django
